{
  "$schema": "https://developer.microsoft.com/json-schemas/spfx-build/spfx-serve.schema.json",
  "port": 4321,
  "https": true,
  "serveConfigurations": {
    "default": {
      "pageUrl": "https://{tenantDomain}/SitePages/myPage.aspx",
      "customActions": {
        "77f39c99-62fe-41b6-b4e2-4bbbd5351557": {
          "location": "ClientSideExtension.ApplicationCustomizer",
          "properties": {
            "testMessage": "Test message"
          }
        }
      }
    },
    "marketingNavigation": {
      "pageUrl": "https://{tenantDomain}/SitePages/myPage.aspx",
      "customActions": {
        "77f39c99-62fe-41b6-b4e2-4bbbd5351557": {
          "location": "ClientSideExtension.ApplicationCustomizer",
          "properties": {
            "testMessage": "Test message"
          }
        }
      }
    }
  },
  "initialPage": "https://{tenantDomain}/_layouts/workbench.aspx"
}
